{"ApprovalTime": "2017-05-19T23:01:08Z", "AutoApprovalTime": "2017-05-19T23:00:27Z", "AssignmentId": "340UGXU9DY1CF7NJU59LARMMGARVUE", "WorkerId": "anon8", "answers": {"data": {"domain": ["monologue", "presentation", "dance", "song"], "knowledge": "unknown", "keyword": ["keyword4", "keyword4", "keyword3", "keyword1"], "goal_thoughts": ["no"], "people": [], "expt_aim": ["seeing if we'd encourage someone that did bad."], "expt": "polgrice_speaker_noGoal", "expt_gen": ["no"], "language": ["english"], "state": ["heart4", "heart3", "heart2", "heart1"], "cond": 3, "numTrials": 4, "posneg": ["posneg1", "posneg1", "posneg1", "posneg1"], "order": [1, 2, 3, 4], "goal": ["both", "both", "both", "both"]}}, "AcceptTime": "2017-05-19T21:59:22Z", "HITId": "3SNR5F7R92TNHL83FWQV20F24OREIJ", "Assignment": "", "AssignmentStatus": "Approved", "SubmitTime": "2017-05-19T22:00:27Z"}