{"ApprovalTime": "2017-05-24T21:53:30Z", "AutoApprovalTime": "2017-05-24T22:46:48Z", "AssignmentId": "3WMINLGALB3W1P3LXJXPKYM3O3HACM", "WorkerId": "anon46", "answers": {"data": {"domain": ["dance", "presentation", "poem", "film", "cookie", "solo", "review", "cake"], "knowledge": "unknown", "keyword": ["keyword4", "keyword4", "keyword3", "keyword1", "keyword3", "keyword4", "keyword1", "keyword0"], "goal_thoughts": ["No"], "people": [], "expt_aim": ["Word choice "], "expt": "polgrice_speaker_pilot2_both_social", "expt_gen": [""], "language": ["English"], "state": ["heart3", "heart4", "heart2", "heart1", "heart3", "heart4", "heart2", "heart1"], "cond": 1, "numTrials": 8, "posneg": ["posneg0", "posneg0", "posneg0", "posneg1", "posneg0", "posneg0", "posneg1", "posneg1"], "order": [1, 2, 3, 4, 5, 6, 7, 8], "goal": ["social", "social", "social", "social", "both", "both", "both", "both"]}}, "AcceptTime": "2017-05-24T21:44:45Z", "HITId": "3QI9WAYOGQB8YKIKEQ1BUETCWPSS6T", "Assignment": "", "AssignmentStatus": "Approved", "SubmitTime": "2017-05-24T21:46:48Z"}