{
    "ApprovalTime": "2015-10-27T00:52:04Z",
    "AutoApprovalTime": "2015-10-27T01:38:49Z",
    "AssignmentId": "34QN5IT0TZRYO9FQO5KRT6E745808C",
    "WorkerId": "A2O4D0WJS54KCO",
    "answers": {
        "data": {
            "domain": [
                "solo",
                "cake",
                "song",
                "song",
                "poem",
                "poem",
                "monologue",
                "app",
                "presentation",
                "monologue",
                "review",
                "presentation",
                "painting",
                "review",
                "dance",
                "cake",
                "film",
                "painting",
                "film",
                "recital",
                "solo",
                "cookie",
                "app",
                "recital",
                "dance"
            ],
            "people": [],
            "expt_gen": [
                "Nope!"
            ],
            "inferredProb0": [
                0.5,
                1,
                0.925,
                0.925,
                0.5,
                0,
                0.95,
                0.225,
                0.75,
                0.95,
                0.95,
                0.5,
                0.25,
                0.75,
                0.025,
                0.725,
                0.275,
                0.75,
                0.5,
                0.25,
                0.1,
                0.25,
                0.95,
                0.75,
                0.225
            ],
            "inferredProb2": [
                0.2,
                0.025,
                0.025,
                0.05,
                0.5,
                1,
                0.05,
                0.8,
                0.35,
                0.025,
                0.075,
                0.3,
                0.75,
                0.225,
                1,
                0.05,
                0.8,
                0.275,
                0.125,
                0.75,
                0.95,
                0.025,
                0.025,
                0,
                0.925
            ],
            "goal2": "mean",
            "goal0": "nice",
            "goal1": "honest",
            "prediction1": "ask",
            "knowledge": "unknown",
            "state": [
                "okay",
                "good",
                "amazing",
                "bad",
                "good",
                "amazing",
                "bad",
                "okay",
                "okay",
                "amazing",
                "terrible",
                "bad",
                "okay",
                "okay",
                "amazing",
                "terrible",
                "amazing",
                "bad",
                "terrible",
                "bad",
                "good",
                "terrible",
                "terrible",
                "good",
                "good"
            ],
            "goal_thoughts": [
                "I am not sure"
            ],
            "predictedProb1": [
                0.775,
                0.85,
                0.875,
                0.75,
                0.5,
                0.075,
                0.725,
                0.25,
                0.725,
                0.85,
                0.75,
                0.725,
                0.3,
                0.75,
                0.1,
                0.675,
                0.225,
                0.7,
                0.65,
                0.375,
                0.25,
                0.7,
                0.625,
                0.725,
                0.225
            ],
            "predictedProb0": [
                0.75,
                0.9,
                0.9,
                0.75,
                0.5,
                0.1,
                0.75,
                0.25,
                0.725,
                0.85,
                0.7,
                0.725,
                0.3,
                0.75,
                0.075,
                0.675,
                0.25,
                0.675,
                0.675,
                0.375,
                0.25,
                0.7,
                0.65,
                0.75,
                0.2
            ],
            "inferredProb1": [
                0.95,
                0.975,
                0.95,
                0.225,
                0.5,
                0,
                0.05,
                0.5,
                0.3,
                0.95,
                0.05,
                0.975,
                0.5,
                0.5,
                0.05,
                0.225,
                0.25,
                0.5,
                0.975,
                0.5,
                0.175,
                0.95,
                0,
                0.75,
                0.15
            ],
            "language": [
                "English"
            ],
            "expt_aim": [
                "I am not sure"
            ],
            "prediction0": "like",
            "expt": "adj_goalPos",
            "numTrials": 25,
            "utterance": [
                "okay",
                "good",
                "amazing",
                "good",
                "okay",
                "terrible",
                "amazing",
                "terrible",
                "amazing",
                "good",
                "amazing",
                "bad",
                "bad",
                "good",
                "bad",
                "okay",
                "okay",
                "okay",
                "bad",
                "terrible",
                "terrible",
                "terrible",
                "good",
                "amazing",
                "bad"
            ],
            "order": [
                1,
                2,
                3,
                4,
                5,
                6,
                7,
                8,
                9,
                10,
                11,
                12,
                13,
                14,
                15,
                16,
                17,
                18,
                19,
                20,
                21,
                22,
                23,
                24,
                25
            ]
        }
    },
    "AcceptTime": "2015-10-27T00:32:51Z",
    "HITId": "3511RHPADVEEGQLEM578TN6DVXGRLJ",
    "Assignment": "",
    "AssignmentStatus": "Approved",
    "SubmitTime": "2015-10-27T00:38:49Z"
}